{
  "date": "2026-02-20",
  "composite": 0.0744419675905659,
  "signal": "NEUTRAL",
  "confidence": 0.1488839351811318,
  "spyPrice": 689.43,
  "spyChange": 4.95,
  "spyChangePct": 0.0,
  "factors": {
    "options": {
      "score": 0.03559942144329242,
      "weight": 0.3,
      "weighted": 0.0107,
      "label": "Options Flow",
      "signals": [
        {
          "name": "Gex",
          "value": null,
          "zScore": 0,
          "interpretation": "Neutral GEX"
        },
        {
          "name": "Iv Term Structure",
          "value": 0.9052,
          "zScore": 0,
          "interpretation": "Contango (calm)"
        },
        {
          "name": "Put Skew 25D",
          "value": 0.1112,
          "zScore": 0,
          "interpretation": "Steep skew (fear)"
        },
        {
          "name": "Zero Dte Share",
          "value": 0.9704,
          "zScore": 0,
          "interpretation": "High 0DTE (>60%)"
        }
      ],
      "lastUpdated": "2026-02-20 22:30:47"
    },
    "macro": {
      "score": 0.3831014666077577,
      "weight": 0.2,
      "weighted": 0.0766,
      "label": "Macro",
      "signals": [
        {
          "name": "Hy Credit Spread",
          "value": 0.1979,
          "zScore": 0,
          "interpretation": "Tight (risk-on)"
        },
        {
          "name": "Macro Surprise",
          "value": 25.7,
          "zScore": 0,
          "interpretation": "Beating expectations"
        },
        {
          "name": "Vix Vix3M Ratio",
          "value": 0.9052,
          "zScore": 0,
          "interpretation": "Contango (calm)"
        },
        {
          "name": "Yield Curve 2S10S",
          "value": 0.2812,
          "zScore": 0,
          "interpretation": "Positive slope (healthy)"
        }
      ],
      "lastUpdated": "2026-02-20 22:30:47"
    },
    "microstructure": {
      "score": -0.31042187288436535,
      "weight": 0.2,
      "weighted": -0.0621,
      "label": "Microstructure",
      "signals": [
        {
          "name": "Block Trade Imbalance",
          "value": 0.0164,
          "zScore": 0,
          "interpretation": "Normal"
        },
        {
          "name": "Dark Pool Pct",
          "value": 0.4359,
          "zScore": 0,
          "interpretation": "Normal off-exchange"
        },
        {
          "name": "Finra Adf Off Exchange Pct",
          "value": 0.3457,
          "zScore": 0,
          "interpretation": "High ADF volume (>15%)"
        },
        {
          "name": "Short Volume Ratio",
          "value": 0.5127,
          "zScore": 0,
          "interpretation": "Normal"
        }
      ],
      "lastUpdated": "2026-02-20 22:30:47"
    },
    "flows": {
      "score": 0.2537328484954321,
      "weight": 0.15,
      "weighted": 0.0381,
      "label": "Systematic Flows",
      "signals": [
        {
          "name": "Cftc Net Spec",
          "value": 976865.0,
          "zScore": 0,
          "interpretation": "Net long"
        },
        {
          "name": "Cta Momentum",
          "value": 1.0,
          "zScore": 0,
          "interpretation": "Following trend up"
        },
        {
          "name": "Month End Rebal",
          "value": 0.0,
          "zScore": 0,
          "interpretation": "No effect"
        },
        {
          "name": "Vol Target Alloc",
          "value": 1.2681,
          "zScore": 0,
          "interpretation": "Near max \u2192 vulnerable"
        }
      ],
      "lastUpdated": "2026-02-20 22:30:47"
    },
    "technical": {
      "score": 0.0,
      "weight": 0.15,
      "weighted": 0.0,
      "label": "Technical",
      "signals": [
        {
          "name": "Price Vs 20Dma",
          "value": null,
          "zScore": 0,
          "interpretation": "Below 20D (bearish)"
        },
        {
          "name": "Price Vs 50Dma",
          "value": null,
          "zScore": 0,
          "interpretation": "Below 50D (bearish)"
        },
        {
          "name": "Rsi 14",
          "value": null,
          "zScore": 0,
          "interpretation": "Mid-range (neutral)"
        },
        {
          "name": "Volume Ratio",
          "value": null,
          "zScore": 0,
          "interpretation": "Below avg volume"
        }
      ],
      "lastUpdated": "2026-02-20 22:30:47"
    },
    "sentiment": {
      "score": -0.307770958129028,
      "weight": 0.0,
      "weighted": -0.0,
      "label": "Sentiment",
      "signals": [
        {
          "name": "Aaii Bull Bear",
          "value": -2.41,
          "zScore": 0,
          "interpretation": "Balanced"
        },
        {
          "name": "Naaim Exposure",
          "value": 82.87,
          "zScore": 0,
          "interpretation": "High exposure (contrarian bear)"
        },
        {
          "name": "News Sentiment",
          "value": 0.1992,
          "zScore": 0,
          "interpretation": "Slightly positive"
        }
      ],
      "lastUpdated": "2026-02-20 22:30:47"
    }
  },
  "alerts": [
    {
      "type": "calendar",
      "severity": "medium",
      "text": "Upcoming high-impact: Core PCE 02-20, GDP (Advance) 02-20, PPI 02-27"
    },
    {
      "type": "calendar",
      "severity": "low",
      "text": "Also scheduled: Consumer Confidence 02-24, New Home Sales 02-25, Initial Jobless Claims 02-26"
    }
  ],
  "lastUpdate": "2026-02-20 22:30:47",
  "exportedAt": "2026-02-20T16:30:47.694447"
}