{
  "date": "2026-04-20",
  "composite": 0.27803281108738387,
  "signal": "BUY",
  "confidence": 0.5560656221747677,
  "spyPrice": 708.72,
  "spyChange": -1.42,
  "spyChangePct": 0.0,
  "factors": {
    "options": {
      "score": -0.04763236250078112,
      "weight": 0.3,
      "weighted": -0.0143,
      "label": "Options Flow",
      "signals": [
        {
          "name": "Gex",
          "value": null,
          "zScore": 0,
          "interpretation": "Neutral GEX"
        },
        {
          "name": "Iv Term Structure",
          "value": 0.8884,
          "zScore": 0,
          "interpretation": "Contango (calm)"
        },
        {
          "name": "Put Skew 25D",
          "value": 0.0718,
          "zScore": 0,
          "interpretation": "Normal skew"
        },
        {
          "name": "Zero Dte Share",
          "value": 0.9747,
          "zScore": 0,
          "interpretation": "High 0DTE (>60%)"
        }
      ],
      "lastUpdated": "2026-04-20 21:31:34"
    },
    "macro": {
      "score": 0.03960579667156226,
      "weight": 0.2,
      "weighted": 0.0079,
      "label": "Macro",
      "signals": [
        {
          "name": "Hy Credit Spread",
          "value": 0.7754,
          "zScore": 0,
          "interpretation": "Tight (risk-on)"
        },
        {
          "name": "Macro Surprise",
          "value": 5.6,
          "zScore": 0,
          "interpretation": "In-line"
        },
        {
          "name": "Vix Vix3M Ratio",
          "value": 0.8884,
          "zScore": 0,
          "interpretation": "Contango (calm)"
        },
        {
          "name": "Yield Curve 2S10S",
          "value": -1.3359,
          "zScore": 0,
          "interpretation": "Inverted (recession signal)"
        }
      ],
      "lastUpdated": "2026-04-20 21:31:34"
    },
    "microstructure": {
      "score": 1.0,
      "weight": 0.2,
      "weighted": 0.2,
      "label": "Microstructure",
      "signals": [
        {
          "name": "Block Trade Imbalance",
          "value": null,
          "zScore": 0,
          "interpretation": "Normal"
        },
        {
          "name": "Dark Pool Pct",
          "value": null,
          "zScore": 0,
          "interpretation": "Low off-exchange"
        },
        {
          "name": "Finra Adf Off Exchange Pct",
          "value": 0.4904,
          "zScore": 0,
          "interpretation": "High ADF volume (>15%)"
        },
        {
          "name": "Short Volume Ratio",
          "value": null,
          "zScore": 0,
          "interpretation": "Below average"
        }
      ],
      "lastUpdated": "2026-04-20 21:31:34"
    },
    "flows": {
      "score": 0.02931917589894602,
      "weight": 0.15,
      "weighted": 0.0044,
      "label": "Systematic Flows",
      "signals": [
        {
          "name": "Cftc Net Spec",
          "value": 1003143.0,
          "zScore": 0,
          "interpretation": "Net long"
        },
        {
          "name": "Cta Momentum",
          "value": 1.0,
          "zScore": 0,
          "interpretation": "Following trend up"
        },
        {
          "name": "Month End Rebal",
          "value": 0.0,
          "zScore": 0,
          "interpretation": "No effect"
        },
        {
          "name": "Vol Target Alloc",
          "value": 0.8343,
          "zScore": 0,
          "interpretation": "Low alloc \u2192 room to add"
        }
      ],
      "lastUpdated": "2026-04-20 21:31:34"
    },
    "technical": {
      "score": 0.5333565607897589,
      "weight": 0.15,
      "weighted": 0.08,
      "label": "Technical",
      "signals": [
        {
          "name": "Price Vs 20Dma",
          "value": 5.8384,
          "zScore": 0,
          "interpretation": "Above 20D (bullish)"
        },
        {
          "name": "Price Vs 50Dma",
          "value": 4.9002,
          "zScore": 0,
          "interpretation": "Above 50D (bullish)"
        },
        {
          "name": "Rsi 14",
          "value": 97.68,
          "zScore": 0,
          "interpretation": "Overbought"
        },
        {
          "name": "Volume Ratio",
          "value": 0.468,
          "zScore": 0,
          "interpretation": "Below avg volume"
        }
      ],
      "lastUpdated": "2026-04-20 21:31:34"
    },
    "sentiment": {
      "score": -0.1696775358513262,
      "weight": 0.0,
      "weighted": -0.0,
      "label": "Sentiment",
      "signals": [
        {
          "name": "Aaii Bull Bear",
          "value": -11.06,
          "zScore": 0,
          "interpretation": "Bearish spread"
        },
        {
          "name": "Naaim Exposure",
          "value": 79.49,
          "zScore": 0,
          "interpretation": "Moderate"
        },
        {
          "name": "News Sentiment",
          "value": 0.0504,
          "zScore": 0,
          "interpretation": "Slightly positive"
        }
      ],
      "lastUpdated": "2026-04-20 21:31:34"
    }
  },
  "alerts": [
    {
      "type": "signal",
      "severity": "high",
      "text": "Microstructure factor at extreme bullish level (+1.00)"
    },
    {
      "type": "calendar",
      "severity": "low",
      "text": "Also scheduled: Initial Jobless Claims 04-23, New Home Sales 04-23"
    }
  ],
  "lastUpdate": "2026-04-20 21:31:34",
  "exportedAt": "2026-04-20T16:31:35.276645"
}